CHANGES.md
MANIFEST.in
README.md
setup.py
bin/lnkr
lnkr/__init__.py
lnkr/app_config.py
lnkr/export_section.py
lnkr/file_config.py
lnkr/folder_config.py
lnkr/import_section.py
lnkr/lnkr.py
lnkr/package_config.py
lnkr/processor.py
lnkr/term.py
lnkr/toml_config.py
lnkr/wrapper_config.py
lnkr.egg-info/PKG-INFO
lnkr.egg-info/SOURCES.txt
lnkr.egg-info/dependency_links.txt
lnkr.egg-info/requires.txt
lnkr.egg-info/top_level.txt